Workbook

Sheet Instrucciones
B2: Fase 3 — Modelo financiero: heladería italiana en Medellín
B5: Cómo está montado este libro:
B6: 1. CAPEX: inversión inicial. La mantecadora ya viene con tu dato real. Rellena en amarillo el resto.
B7: 2. Costo_Materia_Prima: parte de tu coste real de Giotto (4€/litro) y lo ajusta a Colombia.
B8: 3. OPEX_Mensual: gastos fijos mensuales del negocio. Rellena en amarillo.
B9: 4. Pricing_PuntoEquilibrio: aquí defines el precio de venta y ves cuántas bolas/mes necesitas vender para no perder dinero.
B10: 5. Proyeccion_12M: con todo lo anterior, proyecta 12 meses en 3 escenarios (conservador/realista/optimista).
B12: Todo lo amarillo lo rellenas tú. Todo lo blanco con fórmulas (letra negra) se calcula solo — no lo toques.
B13: El tipo de cambio EUR/COP es editable en Costo_Materia_Prima por si cambia mucho con el tiempo.

Sheet CAPEX
A1: 59
B2: Inversión inicial (CAPEX) — en COP
B4: Concepto | C4: Costo estimado (COP) | D4: Fuente / Nota
B5: Mantecadora profesional (batch freezer) | C5: 77700000 | D5: 15.000€ x factor 1,40 (IVA+flete+seguro+agente aduanas) x 3.700 COP/€
B6: Abatidor de temperatura | C6: 7851000 | D6: Pendiente de cotizar. Si se importa de España, aplica el mismo factor ~1,35-1,50 antes de convertir a COP
B7: Vitrina expositora (pozzetti) | C7: 59600000 | D7: Pendiente de cotizar. Si se importa de España, aplica el mismo factor ~1,35-1,50 antes de convertir a COP
B8: Pasteurizadora | C8: 67374000
B9: Cámara de conservación / congelador | C9: 14000000 | D9: Pendiente de cotizar
B10: Acondicionamiento de local (obra + mobiliario) | C10: 130000000 | D10: Estimado: 65 m² x ~2.000.000 COP/m² (acabado medio-alto, instalaciones incluidas)
B11: Licencias y trámites de apertura en Colombia | C11: 3000000 | D11: Pendiente de investigar
B12: Capital de trabajo inicial (imprevistos, 1er mes) | C12: 15500000 | D12: Sugerido: 1 mes de OPEX total
B13: TOTAL CAPEX | C13: =SUM(C5:C12) -> 375025000
B15: Supuestos usados: tamaño de local 65 m² (estándar heladería italiana artesanal: 50-80 m²). Maquinaria importada de España: aplica factor 1,35-1,50 sobre el precio en euros ANTES de convertir a COP (cubre IVA 19%, flete+seguro, agente de aduanas; usa 1,35 si gestionas certificado de origen UE con arancel 0%, o hasta 1,50 sin él). Tipo de cambio usado: 3.700 COP/€.

Sheet Costo_Materia_Prima
B2: Costo de materia prima por litro — ajustado a Colombia
B5: Coste real de materia prima en Giotto (España) | E5: 4 | F5: €/litro
B6: Tipo de cambio EUR/COP (editable) | E6: 3700 | F6: COP por 1€
B7: Coste base en COP/litro | E7: =E5*E6 -> 14800 | F7: resultado: fila anterior x tipo de cambio
B9: Ajuste sabores 100% locales (fruta tropical, sin importación) | E9: -15 | F9: % respecto al coste base
B10: Ajuste sabores premium europeos (con insumo importado: pistacho, avellana, chocolate) | E10: 30 | F10: % respecto al coste base
B11: Coste sabores locales (COP/litro) | E11: =E7*(1+E9/100) -> 12580 | F11: calculado
B12: Coste sabores premium europeos (COP/litro) | E12: =E7*(1+E10/100) -> 19240 | F12: calculado
B14: Mix de ventas asumido — % sabores locales | E14: 60 | F14: %, ajusta según investigación de sabores (pregunta 2)
B15: Mix de ventas asumido — % sabores premium europeos | E15: 40 | F15: % (debe sumar 100% con la anterior)
B16: COSTE PONDERADO PROMEDIO (COP/litro) | E16: =E11*E14/100+E12*E15/100 -> 15244 | F16: calculado — este es el dato que alimenta el resto del modelo
B18: Nota: el % de mix local/premium debería salir de la investigación de sabores (pregunta 2 del proyecto). Por ahora es un supuesto de partida (60/40) que puedes ajustar cuando tengas esos datos.

Sheet OPEX_Mensual
B2: Gastos fijos mensuales (OPEX) — en COP
B4: Concepto | C4: Costo mensual (COP) | D4: Nota
B5: Alquiler del local (Medellín) | C5: 4000000 | D5: Usa el dato que ya recolectaste en Costo_Local del scorecard
B6: Personal (nº empleados x salario + prestaciones) | C6: 6000000 | D6: Colombia: recuerda incluir prestaciones sociales (~50% adicional al salario base)
B7: Servicios (agua, luz, gas) | C7: 3000000 | D7: Estimar según tamaño de local
B8: Marketing y redes sociales | C8: 0 | D8: Puede empezar bajo y crecer con el negocio
B9: Insumos no alimentarios (vasos, cucharitas, servilletas) | C9: 2000000 | D9: Estimar % sobre ventas o fijo mensual
B10: Otros gastos fijos (seguros, contabilidad, software) | C10: 500000 | D10: Estimar
B12: TOTAL OPEX MENSUAL | C12: =SUM(C5:C10) -> 15500000

Sheet Pricing_PuntoEquilibrio
B2: Precio de venta y punto de equilibrio
B5: Litros por bola de helado (estándar ~0.09-0.11L) | E5: 0.08 | F5: ajusta según tu tamaño real de bola
B6: Coste materia prima por bola (COP) | E6: =Costo_Materia_Prima!$E$16*E5 -> 1219.52 | F6: resultado: coste ponderado x litros/bola
B7: Precio de venta (PVP) por bola (COP) | E7: 11900 | F7: ajústalo según poder adquisitivo de Medellín (ver Scorecard)
B8: Margen bruto por bola (COP) | E8: =E7-E6 -> 10680.48 | F8: PVP - coste materia prima
B9: Food cost % (coste / PVP) | E9: =E6/E7 -> 0.10248067 | F9: referencia típica heladería: 25-30%
B10: Costos fijos mensuales (OPEX total) | E10: =OPEX_Mensual!$C$12 -> 15500000 | F10: traído automáticamente de OPEX_Mensual
B11: Punto de equilibrio (bolas/mes) | E11: =E10/E8 -> 1451.2456 | F11: costos fijos / margen bruto por bola
B12: Punto de equilibrio (bolas/día, 30 días/mes) | E12: =E11/30 -> 48.374855 | F12: punto de equilibrio mensual / 30

Sheet Proyeccion_12M
B2: Proyección a 12 meses — 3 escenarios
B4: Bolas vendidas por día — supuesto de partida por escenario (x veces el punto de equilibrio diario)
B6: Escenario | C6: Multiplicador vs. punto de equilibrio | D6: Bolas/día resultante
B7: Conservador | C7: 1 | D7: =Pricing_PuntoEquilibrio!$E$12*C7 -> 48.374855
B8: Realista | C8: 2.1 | D8: =Pricing_PuntoEquilibrio!$E$12*C8 -> 101.58719
B9: Optimista | C9: 3 | D9: =Pricing_PuntoEquilibrio!$E$12*C9 -> 145.12456
B11: Detalle mensual (12 meses) — cambia el escenario en la celda de abajo
B12: Escenario a proyectar: | C12: optimista
B14: Mes | C14: Bolas vendidas | D14: Ingresos (COP) | E14: Coste materia prima (COP) | F14: Margen bruto (COP) | G14: OPEX (COP) | H14: Resultado mensual (COP) | I14: Resultado acumulado (COP)
B15: 1 | C15: =INDEX($D$7:$D$9,MATCH($C$12,$B$7:$B$9,0))*30 -> 4353.7369 | D15: =C15*Pricing_PuntoEquilibrio!$E$7 -> 51809469 | E15: =C15*Pricing_PuntoEquilibrio!$E$6 -> 5309469.2 | F15: =D15-E15 -> 46500000 | G15: =OPEX_Mensual!$C$12 -> 15500000 | H15: =F15-G15 -> 31000000 | I15: =H15 -> 31000000
B16: 2 | C16: =INDEX($D$7:$D$9,MATCH($C$12,$B$7:$B$9,0))*30 -> 4353.7369 | D16: =C16*Pricing_PuntoEquilibrio!$E$7 -> 51809469 | E16: =C16*Pricing_PuntoEquilibrio!$E$6 -> 5309469.2 | F16: =D16-E16 -> 46500000 | G16: =OPEX_Mensual!$C$12 -> 15500000 | H16: =F16-G16 -> 31000000 | I16: =I15+H16 -> 62000000
B17: 3 | C17: =INDEX($D$7:$D$9,MATCH($C$12,$B$7:$B$9,0))*30 -> 4353.7369 | D17: =C17*Pricing_PuntoEquilibrio!$E$7 -> 51809469 | E17: =C17*Pricing_PuntoEquilibrio!$E$6 -> 5309469.2 | F17: =D17-E17 -> 46500000 | G17: =OPEX_Mensual!$C$12 -> 15500000 | H17: =F17-G17 -> 31000000 | I17: =I16+H17 -> 93000000
B18: 4 | C18: =INDEX($D$7:$D$9,MATCH($C$12,$B$7:$B$9,0))*30 -> 4353.7369 | D18: =C18*Pricing_PuntoEquilibrio!$E$7 -> 51809469 | E18: =C18*Pricing_PuntoEquilibrio!$E$6 -> 5309469.2 | F18: =D18-E18 -> 46500000 | G18: =OPEX_Mensual!$C$12 -> 15500000 | H18: =F18-G18 -> 31000000 | I18: =I17+H18 -> 124000000
B19: 5 | C19: =INDEX($D$7:$D$9,MATCH($C$12,$B$7:$B$9,0))*30 -> 4353.7369 | D19: =C19*Pricing_PuntoEquilibrio!$E$7 -> 51809469 | E19: =C19*Pricing_PuntoEquilibrio!$E$6 -> 5309469.2 | F19: =D19-E19 -> 46500000 | G19: =OPEX_Mensual!$C$12 -> 15500000 | H19: =F19-G19 -> 31000000 | I19: =I18+H19 -> 155000000
B20: 6 | C20: =INDEX($D$7:$D$9,MATCH($C$12,$B$7:$B$9,0))*30 -> 4353.7369 | D20: =C20*Pricing_PuntoEquilibrio!$E$7 -> 51809469 | E20: =C20*Pricing_PuntoEquilibrio!$E$6 -> 5309469.2 | F20: =D20-E20 -> 46500000 | G20: =OPEX_Mensual!$C$12 -> 15500000 | H20: =F20-G20 -> 31000000 | I20: =I19+H20 -> 186000000
B21: 7 | C21: =INDEX($D$7:$D$9,MATCH($C$12,$B$7:$B$9,0))*30 -> 4353.7369 | D21: =C21*Pricing_PuntoEquilibrio!$E$7 -> 51809469 | E21: =C21*Pricing_PuntoEquilibrio!$E$6 -> 5309469.2 | F21: =D21-E21 -> 46500000 | G21: =OPEX_Mensual!$C$12 -> 15500000 | H21: =F21-G21 -> 31000000 | I21: =I20+H21 -> 217000000
B22: 8 | C22: =INDEX($D$7:$D$9,MATCH($C$12,$B$7:$B$9,0))*30 -> 4353.7369 | D22: =C22*Pricing_PuntoEquilibrio!$E$7 -> 51809469 | E22: =C22*Pricing_PuntoEquilibrio!$E$6 -> 5309469.2 | F22: =D22-E22 -> 46500000 | G22: =OPEX_Mensual!$C$12 -> 15500000 | H22: =F22-G22 -> 31000000 | I22: =I21+H22 -> 248000000
B23: 9 | C23: =INDEX($D$7:$D$9,MATCH($C$12,$B$7:$B$9,0))*30 -> 4353.7369 | D23: =C23*Pricing_PuntoEquilibrio!$E$7 -> 51809469 | E23: =C23*Pricing_PuntoEquilibrio!$E$6 -> 5309469.2 | F23: =D23-E23 -> 46500000 | G23: =OPEX_Mensual!$C$12 -> 15500000 | H23: =F23-G23 -> 31000000 | I23: =I22+H23 -> 279000000
B24: 10 | C24: =INDEX($D$7:$D$9,MATCH($C$12,$B$7:$B$9,0))*30 -> 4353.7369 | D24: =C24*Pricing_PuntoEquilibrio!$E$7 -> 51809469 | E24: =C24*Pricing_PuntoEquilibrio!$E$6 -> 5309469.2 | F24: =D24-E24 -> 46500000 | G24: =OPEX_Mensual!$C$12 -> 15500000 | H24: =F24-G24 -> 31000000 | I24: =I23+H24 -> 310000000
B25: 11 | C25: =INDEX($D$7:$D$9,MATCH($C$12,$B$7:$B$9,0))*30 -> 4353.7369 | D25: =C25*Pricing_PuntoEquilibrio!$E$7 -> 51809469 | E25: =C25*Pricing_PuntoEquilibrio!$E$6 -> 5309469.2 | F25: =D25-E25 -> 46500000 | G25: =OPEX_Mensual!$C$12 -> 15500000 | H25: =F25-G25 -> 31000000 | I25: =I24+H25 -> 341000000
B26: 12 | C26: =INDEX($D$7:$D$9,MATCH($C$12,$B$7:$B$9,0))*30 -> 4353.7369 | D26: =C26*Pricing_PuntoEquilibrio!$E$7 -> 51809469 | E26: =C26*Pricing_PuntoEquilibrio!$E$6 -> 5309469.2 | F26: =D26-E26 -> 46500000 | G26: =OPEX_Mensual!$C$12 -> 15500000 | H26: =F26-G26 -> 31000000 | I26: =I25+H26 -> 372000000
B28: Cambia la celda 'Escenario a proyectar' (Conservador/Realista/Optimista) para ver cómo cambia toda la tabla. El mes en que el 'Resultado acumulado' se vuelve positivo es, aproximadamente, cuándo recuperas la inversión (CAPEX) — compáralo con el total de la pestaña CAPEX.
