Workbook

Sheet Clima
A2: Ciudad | B2: Temp. media anual (°C) | C2: Puntuación (1-5) | D2: Fuente (link) | E2: Fecha consulta
A3: Bogotá | B3: 13.1 | C3: 1 | D3: IDEAM (via bogota.gov.co) | E3: 2026-07-11
A4: Medellín | B4: 22 | C4: 4.5 | D4: Weather Spark (rango 16-26°C) | E4: 2026-07-11
A5: Cali | B5: 24 | C5: 4 | D5: Clasificación climática MinVivienda (cálido seco) | E5: 2026-07-11
A6: Barranquilla | B6: 28 | C6: 3.5 | D6: clima.com / clasificación cálido húmedo | E6: 2026-07-11
A7: Cartagena | B7: 27.5 | C7: 3.5 | D7: clima.com / clasificación cálido húmedo | E7: 2026-07-11
A8: Bucaramanga | B8: 23 | C8: 4.5 | D8: clima.com / clasificación cálido seco | E8: 2026-07-11
A9: Pereira | B9: 21 | C9: 4.5 | D9: Clasificación climática MinVivienda (templado) | E9: 2026-07-11
A10: Santa Marta | B10: 28 | C10: 3.5 | D10: clima.com / clasificación cálido húmedo | E10: 2026-07-11

Sheet Poder_Adquisitivo
A2: Ciudad | B2: % Incidencia pobreza monetaria (2025) (%) | C2: Puntuación (1-5) | D2: Fuente (link) | E2: Fecha consulta
A3: Bogotá | B3: 17.8 | C3: =IFERROR(1+4*(MAX(B$3:B$10)-B3)/(MAX(B$3:B$10)-MIN(B$3:B$10)),"") -> 4.7541899 | D3: DANE, Boletín Pobreza Monetaria 2025 | E3: 2026-07-11
A4: Medellín | B4: 16.7 | C4: =IFERROR(1+4*(MAX(B$3:B$10)-B4)/(MAX(B$3:B$10)-MIN(B$3:B$10)),"") -> 5 | D4: DANE, Boletín Pobreza Monetaria 2025 | E4: 2026-07-11
A5: Cali | B5: 19.7 | C5: =IFERROR(1+4*(MAX(B$3:B$10)-B5)/(MAX(B$3:B$10)-MIN(B$3:B$10)),"") -> 4.3296089 | D5: DANE, Boletín Pobreza Monetaria 2025 | E5: 2026-07-11
A6: Barranquilla | B6: 23.4 | C6: =IFERROR(1+4*(MAX(B$3:B$10)-B6)/(MAX(B$3:B$10)-MIN(B$3:B$10)),"") -> 3.5027933 | D6: DANE, Boletín Pobreza Monetaria 2025 | E6: 2026-07-11
A7: Cartagena | B7: 34.6 | C7: =IFERROR(1+4*(MAX(B$3:B$10)-B7)/(MAX(B$3:B$10)-MIN(B$3:B$10)),"") -> 1 | D7: DANE, Boletín Pobreza Monetaria 2025 | E7: 2026-07-11
A8: Bucaramanga | B8: 28.4 | C8: =IFERROR(1+4*(MAX(B$3:B$10)-B8)/(MAX(B$3:B$10)-MIN(B$3:B$10)),"") -> 2.3854749 | D8: DANE, Boletín Pobreza Monetaria 2025 | E8: 2026-07-11
A9: Pereira | B9: 21.2 | C9: =IFERROR(1+4*(MAX(B$3:B$10)-B9)/(MAX(B$3:B$10)-MIN(B$3:B$10)),"") -> 3.9944134 | D9: DANE, Boletín Pobreza Monetaria 2025 | E9: 2026-07-11
A10: Santa Marta | B10: 28.6 | C10: =IFERROR(1+4*(MAX(B$3:B$10)-B10)/(MAX(B$3:B$10)-MIN(B$3:B$10)),"") -> 2.3407821 | D10: DANE, Boletín Pobreza Monetaria 2025 | E10: 2026-07-11
A12: Proxy usado: % de incidencia de pobreza monetaria (DANE 2025). A MENOR pobreza, MEJOR poder adquisitivo — por eso la puntuación se calcula de forma invertida (higher_is_better=False). Si luego encuentras el ingreso promedio exacto por ciudad, puedes sustituir el valor y cambiar a higher_is_better=True.

Sheet Turismo
A2: Ciudad | B2: Turistas extranjeros / año (personas/año) | C2: Puntuación (1-5) | D2: Fuente (link) | E2: Fecha consulta
A3: Bogotá | B3: 1975000 | C3: =IFERROR(1+4*(B3-MIN(B$3:B$10))/(MAX(B$3:B$10)-MIN(B$3:B$10)),"") -> 2.412844 | D3: https://observatorio.idt.gov.co/publicaciones/investigacion-viajeros-en-bogota-2025
A4: Medellín | B4: 1200000 | C4: =IFERROR(1+4*(B4-MIN(B$3:B$10))/(MAX(B$3:B$10)-MIN(B$3:B$10)),"") -> 1.8440367 | D4: https://www.turismomde.gov.co/
A5: Cali | B5: 300000 | C5: =IFERROR(1+4*(B5-MIN(B$3:B$10))/(MAX(B$3:B$10)-MIN(B$3:B$10)),"") -> 1.1834862 | D5: https://pre-webunwto.s3.eu-west-1.amazonaws.com/s3fs-public/2026-05/2026%20Annual%20Report%20of%20Cali%20Tourism%20Observatory%20%E2%80%93%20SITUR%20Valle%20del%20Cauca%20(Data%202025)_Espa%C3%B1ol.pdf?VersionId=S00KXdX9gomqof6iXU9jhGLDgWEBGZbJ
A6: Barranquilla | B6: 1600000 | C6: =IFERROR(1+4*(B6-MIN(B$3:B$10))/(MAX(B$3:B$10)-MIN(B$3:B$10)),"") -> 2.1376147 | D6: https://www.instagram.com/p/DVPdBF-CulF/
A7: Cartagena | B7: 5500000 | C7: =IFERROR(1+4*(B7-MIN(B$3:B$10))/(MAX(B$3:B$10)-MIN(B$3:B$10)),"") -> 5 | D7: https://www.cartagena.gov.co/noticias/corpoturismo-presento-exitoso-balance-promocion-cartagena-2025-55-millones-turistas-llegaron-este-ano
A8: Bucaramanga | B8: 400000 | C8: =IFERROR(1+4*(B8-MIN(B$3:B$10))/(MAX(B$3:B$10)-MIN(B$3:B$10)),"") -> 1.2568807
A9: Pereira | B9: 50000 | C9: =IFERROR(1+4*(B9-MIN(B$3:B$10))/(MAX(B$3:B$10)-MIN(B$3:B$10)),"") -> 1
A10: Santa Marta | B10: 72000 | C10: =IFERROR(1+4*(B10-MIN(B$3:B$10))/(MAX(B$3:B$10)-MIN(B$3:B$10)),"") -> 1.0161468
A12: Fuente sugerida: MinCIT, Migración Colombia, boletines COTELCO (ocupación hotelera).

Sheet Costo_Local
A2: Ciudad | B2: Precio arriendo local comercial (COP/m²/mes) | C2: Puntuación (1-5) | D2: Fuente (link) | E2: Fecha consulta
A3: Bogotá | B3: 100000 | C3: =IFERROR(1+4*(MAX(B$3:B$10)-B3)/(MAX(B$3:B$10)-MIN(B$3:B$10)),"") -> 3.9090909 | D3: https://www.fincaraiz.com.co/arriendo/locales/bogota/bogota-dc
A4: Medellín | B4: 110000 | C4: =IFERROR(1+4*(MAX(B$3:B$10)-B4)/(MAX(B$3:B$10)-MIN(B$3:B$10)),"") -> 3.5454545 | D4: https://www.properati.com.co/s/medellin-antioquia/local/arriendo
A5: Cali | B5: 75000 | C5: =IFERROR(1+4*(MAX(B$3:B$10)-B5)/(MAX(B$3:B$10)-MIN(B$3:B$10)),"") -> 4.8181818 | D5: https://www.fincaraiz.com.co/arriendo/locales/cali/valle-del-cauca
A6: Barranquilla | B6: 70000 | C6: =IFERROR(1+4*(MAX(B$3:B$10)-B6)/(MAX(B$3:B$10)-MIN(B$3:B$10)),"") -> 5 | D6: https://www.properati.com.co/s/barranquilla-atlantico/local/arriendo
A7: Cartagena | B7: 180000 | C7: =IFERROR(1+4*(MAX(B$3:B$10)-B7)/(MAX(B$3:B$10)-MIN(B$3:B$10)),"") -> 1 | D7: https://www.properati.com.co/s/cartagena-bolivar/local/arriendo
A8: Bucaramanga | B8: 94000 | C8: =IFERROR(1+4*(MAX(B$3:B$10)-B8)/(MAX(B$3:B$10)-MIN(B$3:B$10)),"") -> 4.1272727 | D8: https://www.fincaraiz.com.co/arriendo/locales/bucaramanga/santander
A9: Pereira | B9: 115000 | C9: =IFERROR(1+4*(MAX(B$3:B$10)-B9)/(MAX(B$3:B$10)-MIN(B$3:B$10)),"") -> 3.3636364 | D9: https://www.metrocuadrado.com/locales/arriendo/pereira/estrato-6
A10: Santa Marta | B10: 90000 | C10: =IFERROR(1+4*(MAX(B$3:B$10)-B10)/(MAX(B$3:B$10)-MIN(B$3:B$10)),"") -> 4.2727273 | D10: https://www.properati.com.co/s/santa-marta/local/arriendo
A12: Fuente sugerida: Fincaraíz o Metrocuadrado. Toma la media de 5-10 anuncios en zona céntrica/comercial.

Sheet Competencia
A2: Ciudad | B2: Nº heladerías artesanales / gelato (conteo) | C2: Puntuación (1-5) | D2: Fuente (link) | E2: Fecha consulta
A3: Bogotá | B3: 25 | C3: =IFERROR(1+4*(MAX(B$3:B$10)-B3)/(MAX(B$3:B$10)-MIN(B$3:B$10)),"") -> 1 | D3: https://www.tripadvisor.es/Restaurants-g294074-zfd9899-Bogota-Ice_Cream.html
A4: Medellín | B4: 6 | C4: =IFERROR(1+4*(MAX(B$3:B$10)-B4)/(MAX(B$3:B$10)-MIN(B$3:B$10)),"") -> 4.4545455
A5: Cali | B5: 11 | C5: =IFERROR(1+4*(MAX(B$3:B$10)-B5)/(MAX(B$3:B$10)-MIN(B$3:B$10)),"") -> 3.5454545 | D5: https://www.tripadvisor.es/Restaurants-g297475-zfd9899-Cali_Valle_del_Cauca_Department-Ice_Cream.html
A6: Barranquilla | B6: 3 | C6: =IFERROR(1+4*(MAX(B$3:B$10)-B6)/(MAX(B$3:B$10)-MIN(B$3:B$10)),"") -> 5 | D6: https://www.tripadvisor.es/Restaurants-g297473-zfd9899-Barranquilla_Atlantico_Department-Ice_Cream.html
A7: Cartagena | B7: 10 | C7: =IFERROR(1+4*(MAX(B$3:B$10)-B7)/(MAX(B$3:B$10)-MIN(B$3:B$10)),"") -> 3.7272727 | D7: https://www.tripadvisor.co/Restaurants-g3874559-zfd9899-Cartagena_District_Bolivar_Department-Ice_Cream.html
A8: Bucaramanga | B8: 5 | C8: =IFERROR(1+4*(MAX(B$3:B$10)-B8)/(MAX(B$3:B$10)-MIN(B$3:B$10)),"") -> 4.6363636 | D8: https://www.tripadvisor.es/Search?q=heladeria+artesanales+bucaramanga&geo=294074&ssrc=a&searchNearby=false&searchSessionId=0006954c8fc5ecc4.ssid&offset=0
A9: Pereira | B9: 3 | C9: =IFERROR(1+4*(MAX(B$3:B$10)-B9)/(MAX(B$3:B$10)-MIN(B$3:B$10)),"") -> 5 | D9: https://www.tripadvisor.es/Search?q=heladeria+artesanal+pereira&geo=297475&ssrc=a&searchNearby=false&searchSessionId=000727bad8736bc5.ssid&offset=0
A10: Santa Marta | B10: 7 | C10: =IFERROR(1+4*(MAX(B$3:B$10)-B10)/(MAX(B$3:B$10)-MIN(B$3:B$10)),"") -> 4.2727273 | D10: https://www.tripadvisor.es/Restaurants-g297484-zfd9899-Santa_Marta_Santa_Marta_Municipality_Magdalena_Department-Ice_Cream.html
A12: Fuente sugerida: Google Maps, buscando 'heladería artesanal' / 'gelato' por ciudad. Excluye cadenas industriales.

Sheet Consumo_Helado
A2: Ciudad | B2: Puntos de venta de helado por 10.000 hab. (proxy consumo) | C2: Puntuación (1-5) | D2: Fuente (link) | E2: Fecha consulta
A3: Bogotá | B3: 40000 | C3: =IFERROR(1+4*(B3-MIN(B$3:B$10))/(MAX(B$3:B$10)-MIN(B$3:B$10)),"") -> 5 | D3: https://www.portafolio.co/negocios/empresas/los-hogares-protagonizan-la-evolucion-del-consumo-de-helado-en-el-pais-642581
A4: Medellín | B4: 34000 | C4: =IFERROR(1+4*(B4-MIN(B$3:B$10))/(MAX(B$3:B$10)-MIN(B$3:B$10)),"") -> 2.6 | D4: https://bibliotecadigital.udea.edu.co/bitstreams/b165fcc0-28dc-4ee9-ad8c-56fd1268bf41/download
A5: Cali | B5: 31000 | C5: =IFERROR(1+4*(B5-MIN(B$3:B$10))/(MAX(B$3:B$10)-MIN(B$3:B$10)),"") -> 1.4 | D5: https://www.msd-salud-animal.com.co/colombianos-consumen-3-1-litros-de-helado-al-ano-por-persona/
A6: Barranquilla | B6: 34000 | C6: =IFERROR(1+4*(B6-MIN(B$3:B$10))/(MAX(B$3:B$10)-MIN(B$3:B$10)),"") -> 2.6 | D6: https://editorial.goula.lat/crece-venta-de-helado-de-yogurt-en-colombia-asi-conquistan-al-consumidor/
A7: Cartagena | B7: 31000 | C7: =IFERROR(1+4*(B7-MIN(B$3:B$10))/(MAX(B$3:B$10)-MIN(B$3:B$10)),"") -> 1.4 | D7: https://www.msd-salud-animal.com.co/colombianos-consumen-3-1-litros-de-helado-al-ano-por-persona/
A8: Bucaramanga | B8: 30000 | C8: =IFERROR(1+4*(B8-MIN(B$3:B$10))/(MAX(B$3:B$10)-MIN(B$3:B$10)),"") -> 1 | D8: https://www.google.com/search?q=cuanto+litros+de+helado+se+consumen+en+bucaramanga+durante+2025&sca_esv=cbbe4593e2dc44d4&biw=1366&bih=641&sxsrf=APpeQnuFzpR_ymZJ5X250HKTwujqnmjq2Q%3A1783775782008&ei=JkJSasAGwIv27w_c9bTRBg&ved=0ahUKEwjAseHO2sqVAxXAhf0HHdw6LWoQ4dUDCBA&uact=5&oq=cuanto+litros+de+helado+se+consumen+en+bucaramanga+durante+2025&gs_lp=Egxnd3Mtd2l6LXNlcnAiP2N1YW50byBsaXRyb3MgZGUgaGVsYWRvIHNlIGNvbnN1bWVuIGVuIGJ1Y2FyYW1hbmdhIGR1cmFudGUgMjAyNUioIlAAWMIgcAB4AZABAJgB4gGgAecXqgEGMS4yMS4yuAEDyAEA-AEBmAIRoALmEcICBxAjGLACGCfCAgUQABjvBcICCBAAGIAEGKIEwgIEECEYCpgDAJIHBjEuMTUuMaAHlnKyBwYxLjE1LjG4B-YRwgcIMC4xLjMuMTPIB48BgAgB&sclient=gws-wiz-serp
A9: Pereira | B9: 35000 | C9: =IFERROR(1+4*(B9-MIN(B$3:B$10))/(MAX(B$3:B$10)-MIN(B$3:B$10)),"") -> 3 | D9: https://www.msd-salud-animal.com.co/colombianos-consumen-3-1-litros-de-helado-al-ano-por-persona/
A10: Santa Marta | B10: 30000 | C10: =IFERROR(1+4*(B10-MIN(B$3:B$10))/(MAX(B$3:B$10)-MIN(B$3:B$10)),"") -> 1 | D10: https://www.infobae.com/colombia/2024/07/30/a-los-colombianos-les-gusta-comer-helado-con-3-litros-al-ano-por-persona-asi-crece-la-industria-heladera-en-el-pais/
A12: Proxy de consumo real (no hay dato oficial por ciudad). Cuenta en Google Maps TODOS los puntos de venta de helado (artesanales + industriales/cadenas) y divide por población/10.000. Si encuentras un informe con consumo per cápita real (Euromonitor, Fenalco), sustitúyelo por ese dato.

Sheet Scorecard
B2: Scorecard final — Puntuación ponderada por ciudad
A4: Ciudad | B4: Consumo Helado (30%) | C4: Clima (20%) | D4: Poder Adq. (20%) | E4: Turismo (15%) | F4: Costo Local (10%) | G4: Competencia (5%) | H4: SCORE TOTAL | I4: Ranking
A5: Bogotá | B5: {=IFERROR(INDEX(Consumo_Helado!$C$3:$C$10,MATCH($A5,Consumo_Helado!$A$3:$A$10,0))*0.3,0)} -> 1.5 | C5: {=IFERROR(INDEX(Clima!$C$3:$C$10,MATCH($A5,Clima!$A$3:$A$10,0))*0.2,0)} -> 0.2 | D5: {=IFERROR(INDEX(Poder_Adquisitivo!$C$3:$C$10,MATCH($A5,Poder_Adquisitivo!$A$3:$A$10,0))*0.2,0)} -> 0.95083799 | E5: {=IFERROR(INDEX(Turismo!$C$3:$C$10,MATCH($A5,Turismo!$A$3:$A$10,0))*0.15,0)} -> 0.36192661 | F5: {=IFERROR(INDEX(Costo_Local!$C$3:$C$10,MATCH($A5,Costo_Local!$A$3:$A$10,0))*0.1,0)} -> 0.39090909 | G5: {=IFERROR(INDEX(Competencia!$C$3:$C$10,MATCH($A5,Competencia!$A$3:$A$10,0))*0.05,0)} -> 0.05 | H5: =SUM(B5:G5) -> 3.4536737 | I5: =RANK(H5,$H$5:$H$12) -> 2
A6: Medellín | B6: {=IFERROR(INDEX(Consumo_Helado!$C$3:$C$10,MATCH($A6,Consumo_Helado!$A$3:$A$10,0))*0.3,0)} -> 0.78 | C6: {=IFERROR(INDEX(Clima!$C$3:$C$10,MATCH($A6,Clima!$A$3:$A$10,0))*0.2,0)} -> 0.9 | D6: {=IFERROR(INDEX(Poder_Adquisitivo!$C$3:$C$10,MATCH($A6,Poder_Adquisitivo!$A$3:$A$10,0))*0.2,0)} -> 1 | E6: {=IFERROR(INDEX(Turismo!$C$3:$C$10,MATCH($A6,Turismo!$A$3:$A$10,0))*0.15,0)} -> 0.2766055 | F6: {=IFERROR(INDEX(Costo_Local!$C$3:$C$10,MATCH($A6,Costo_Local!$A$3:$A$10,0))*0.1,0)} -> 0.35454545 | G6: {=IFERROR(INDEX(Competencia!$C$3:$C$10,MATCH($A6,Competencia!$A$3:$A$10,0))*0.05,0)} -> 0.22272727 | H6: =SUM(B6:G6) -> 3.5338782 | I6: =RANK(H6,$H$5:$H$12) -> 1
A7: Cali | B7: {=IFERROR(INDEX(Consumo_Helado!$C$3:$C$10,MATCH($A7,Consumo_Helado!$A$3:$A$10,0))*0.3,0)} -> 0.42 | C7: {=IFERROR(INDEX(Clima!$C$3:$C$10,MATCH($A7,Clima!$A$3:$A$10,0))*0.2,0)} -> 0.8 | D7: {=IFERROR(INDEX(Poder_Adquisitivo!$C$3:$C$10,MATCH($A7,Poder_Adquisitivo!$A$3:$A$10,0))*0.2,0)} -> 0.86592179 | E7: {=IFERROR(INDEX(Turismo!$C$3:$C$10,MATCH($A7,Turismo!$A$3:$A$10,0))*0.15,0)} -> 0.17752294 | F7: {=IFERROR(INDEX(Costo_Local!$C$3:$C$10,MATCH($A7,Costo_Local!$A$3:$A$10,0))*0.1,0)} -> 0.48181818 | G7: {=IFERROR(INDEX(Competencia!$C$3:$C$10,MATCH($A7,Competencia!$A$3:$A$10,0))*0.05,0)} -> 0.17727273 | H7: =SUM(B7:G7) -> 2.9225356 | I7: =RANK(H7,$H$5:$H$12) -> 5
A8: Barranquilla | B8: {=IFERROR(INDEX(Consumo_Helado!$C$3:$C$10,MATCH($A8,Consumo_Helado!$A$3:$A$10,0))*0.3,0)} -> 0.78 | C8: {=IFERROR(INDEX(Clima!$C$3:$C$10,MATCH($A8,Clima!$A$3:$A$10,0))*0.2,0)} -> 0.7 | D8: {=IFERROR(INDEX(Poder_Adquisitivo!$C$3:$C$10,MATCH($A8,Poder_Adquisitivo!$A$3:$A$10,0))*0.2,0)} -> 0.70055866 | E8: {=IFERROR(INDEX(Turismo!$C$3:$C$10,MATCH($A8,Turismo!$A$3:$A$10,0))*0.15,0)} -> 0.3206422 | F8: {=IFERROR(INDEX(Costo_Local!$C$3:$C$10,MATCH($A8,Costo_Local!$A$3:$A$10,0))*0.1,0)} -> 0.5 | G8: {=IFERROR(INDEX(Competencia!$C$3:$C$10,MATCH($A8,Competencia!$A$3:$A$10,0))*0.05,0)} -> 0.25 | H8: =SUM(B8:G8) -> 3.2512009 | I8: =RANK(H8,$H$5:$H$12) -> 4
A9: Cartagena | B9: {=IFERROR(INDEX(Consumo_Helado!$C$3:$C$10,MATCH($A9,Consumo_Helado!$A$3:$A$10,0))*0.3,0)} -> 0.42 | C9: {=IFERROR(INDEX(Clima!$C$3:$C$10,MATCH($A9,Clima!$A$3:$A$10,0))*0.2,0)} -> 0.7 | D9: {=IFERROR(INDEX(Poder_Adquisitivo!$C$3:$C$10,MATCH($A9,Poder_Adquisitivo!$A$3:$A$10,0))*0.2,0)} -> 0.2 | E9: {=IFERROR(INDEX(Turismo!$C$3:$C$10,MATCH($A9,Turismo!$A$3:$A$10,0))*0.15,0)} -> 0.75 | F9: {=IFERROR(INDEX(Costo_Local!$C$3:$C$10,MATCH($A9,Costo_Local!$A$3:$A$10,0))*0.1,0)} -> 0.1 | G9: {=IFERROR(INDEX(Competencia!$C$3:$C$10,MATCH($A9,Competencia!$A$3:$A$10,0))*0.05,0)} -> 0.18636364 | H9: =SUM(B9:G9) -> 2.3563636 | I9: =RANK(H9,$H$5:$H$12) -> 7
A10: Bucaramanga | B10: {=IFERROR(INDEX(Consumo_Helado!$C$3:$C$10,MATCH($A10,Consumo_Helado!$A$3:$A$10,0))*0.3,0)} -> 0.3 | C10: {=IFERROR(INDEX(Clima!$C$3:$C$10,MATCH($A10,Clima!$A$3:$A$10,0))*0.2,0)} -> 0.9 | D10: {=IFERROR(INDEX(Poder_Adquisitivo!$C$3:$C$10,MATCH($A10,Poder_Adquisitivo!$A$3:$A$10,0))*0.2,0)} -> 0.47709497 | E10: {=IFERROR(INDEX(Turismo!$C$3:$C$10,MATCH($A10,Turismo!$A$3:$A$10,0))*0.15,0)} -> 0.18853211 | F10: {=IFERROR(INDEX(Costo_Local!$C$3:$C$10,MATCH($A10,Costo_Local!$A$3:$A$10,0))*0.1,0)} -> 0.41272727 | G10: {=IFERROR(INDEX(Competencia!$C$3:$C$10,MATCH($A10,Competencia!$A$3:$A$10,0))*0.05,0)} -> 0.23181818 | H10: =SUM(B10:G10) -> 2.5101725 | I10: =RANK(H10,$H$5:$H$12) -> 6
A11: Pereira | B11: {=IFERROR(INDEX(Consumo_Helado!$C$3:$C$10,MATCH($A11,Consumo_Helado!$A$3:$A$10,0))*0.3,0)} -> 0.9 | C11: {=IFERROR(INDEX(Clima!$C$3:$C$10,MATCH($A11,Clima!$A$3:$A$10,0))*0.2,0)} -> 0.9 | D11: {=IFERROR(INDEX(Poder_Adquisitivo!$C$3:$C$10,MATCH($A11,Poder_Adquisitivo!$A$3:$A$10,0))*0.2,0)} -> 0.79888268 | E11: {=IFERROR(INDEX(Turismo!$C$3:$C$10,MATCH($A11,Turismo!$A$3:$A$10,0))*0.15,0)} -> 0.15 | F11: {=IFERROR(INDEX(Costo_Local!$C$3:$C$10,MATCH($A11,Costo_Local!$A$3:$A$10,0))*0.1,0)} -> 0.33636364 | G11: {=IFERROR(INDEX(Competencia!$C$3:$C$10,MATCH($A11,Competencia!$A$3:$A$10,0))*0.05,0)} -> 0.25 | H11: =SUM(B11:G11) -> 3.3352463 | I11: =RANK(H11,$H$5:$H$12) -> 3
A12: Santa Marta | B12: {=IFERROR(INDEX(Consumo_Helado!$C$3:$C$10,MATCH($A12,Consumo_Helado!$A$3:$A$10,0))*0.3,0)} -> 0.3 | C12: {=IFERROR(INDEX(Clima!$C$3:$C$10,MATCH($A12,Clima!$A$3:$A$10,0))*0.2,0)} -> 0.7 | D12: {=IFERROR(INDEX(Poder_Adquisitivo!$C$3:$C$10,MATCH($A12,Poder_Adquisitivo!$A$3:$A$10,0))*0.2,0)} -> 0.46815642 | E12: {=IFERROR(INDEX(Turismo!$C$3:$C$10,MATCH($A12,Turismo!$A$3:$A$10,0))*0.15,0)} -> 0.15242202 | F12: {=IFERROR(INDEX(Costo_Local!$C$3:$C$10,MATCH($A12,Costo_Local!$A$3:$A$10,0))*0.1,0)} -> 0.42727273 | G12: {=IFERROR(INDEX(Competencia!$C$3:$C$10,MATCH($A12,Competencia!$A$3:$A$10,0))*0.05,0)} -> 0.21363636 | H12: =SUM(B12:G12) -> 2.2614875 | I12: =RANK(H12,$H$5:$H$12) -> 8
A14: La ciudad con SCORE TOTAL más alto (Ranking = 1) es la recomendada por el modelo. Recuerda documentar por qué en tu narrativa: los números apoyan la decisión, no la reemplazan.
